loco_sdk/__init__.py
loco_sdk/version.py
loco_sdk/plugin/__init__.py
loco_sdk/plugin/base.py
loco_sdk/plugin/context.py
loco_sdk/plugin/exceptions.py
loco_sdk/plugin/files.py
loco_sdk/plugin/server/__init__.py
loco_sdk/plugin/server/__main__.py
loco_sdk/plugin/server/server.py
loco_sdk/schemas/__init__.py
loco_sdk/utils/__init__.py
loco_sdk-0.2.2.dist-info/METADATA
loco_sdk-0.2.2.dist-info/WHEEL
loco_sdk-0.2.2.dist-info/top_level.txt
loco_sdk-0.2.2.dist-info/RECORD
